sphinx_readme/__init__.py
sphinx_readme/config.py
sphinx_readme/parser.py
sphinx_readme/utils/__init__.py
sphinx_readme/utils/docutils.py
sphinx_readme/utils/git.py
sphinx_readme/utils/linkcode.py
sphinx_readme/utils/rst.py
sphinx_readme/utils/sphinx.py
sphinx_readme-1.2.1.dist-info/LICENSE
sphinx_readme-1.2.1.dist-info/METADATA
sphinx_readme-1.2.1.dist-info/WHEEL
sphinx_readme-1.2.1.dist-info/top_level.txt
sphinx_readme-1.2.1.dist-info/RECORD
