Metadata-Version: 2.1
Name: sphinx-readme
Version: 1.2.1
Summary: Generate Beautiful reStructuredText README.rst for GitHub, PyPi, GitLab, BitBucket
Home-page: https://github.com/tdkorn/sphinx-readme
Author: Adam Korn
Author-email: hello@dailykitten.net
License: MIT License
Download-URL: https://github.com/TDKorn/sphinx-readme/tarball/main
Keywords: sphinx,docutils,sphinx-extension,sphinx-contrib,reStructuredText,rst,reST,parser,rst-parser,README.rst,README,autodoc,linkcode
Platform: UNKNOWN
Classifier: Framework :: Sphinx :: Extension
Classifier: License :: OSI Approved :: MIT License
Classifier: Programming Language :: Python :: 3
Classifier: Programming Language :: Python :: 3.10
License-File: LICENSE
Requires-Dist: sphinx (>=1.8)
